pyperf/__init__.py
pyperf/apply.py
pyperf/base.py
pyperf/main.py
pyperf/tests/__init__.py
pyperf/tests/classes/__init__.py
pyperf/tests/classes/classes_slots.py
pyperf/tests/dicts/__init__.py
pyperf/tests/dicts/dicts.py
pyperf/tests/lists/__init__.py
pyperf/tests/lists/lists.py
pyperf_test-0.0.5.dist-info/METADATA
pyperf_test-0.0.5.dist-info/WHEEL
pyperf_test-0.0.5.dist-info/top_level.txt
pyperf_test-0.0.5.dist-info/RECORD
