Metadata-Version: 2.1
Name: pyperf-test
Version: 0.0.5
Summary: test python speed
Home-page: https://github.com/maxwolf8852/perf_test.git
Author: Maxim Volkovskiy
Author-email: maxwolf8852@gmail.com
Classifier: Programming Language :: Python :: 3.6
Classifier: License :: OSI Approved :: MIT License
Classifier: Operating System :: OS Independent
Requires-Python: >=3.6
Requires-Dist: colorama
Requires-Dist: tqdm
